pybotterfly/__init__.py
pybotterfly/base_config.py
pybotterfly/bot/__init__.py
pybotterfly/bot/converters.py
pybotterfly/bot/downloaders.py
pybotterfly/bot/logger.py
pybotterfly/bot/reply/__init__.py
pybotterfly/bot/reply/default_reply_types.py
pybotterfly/bot/reply/reply_division.py
pybotterfly/bot/returns/__init__.py
pybotterfly/bot/returns/buttons.py
pybotterfly/bot/returns/message.py
pybotterfly/bot/struct.py
pybotterfly/bot/throttlers.py
pybotterfly/bot/transitions/__init__.py
pybotterfly/bot/transitions/payloads.py
pybotterfly/bot/transitions/schedule.py
pybotterfly/bot/transitions/transitions.py
pybotterfly/message_handler/__init__.py
pybotterfly/message_handler/message_handler.py
pybotterfly/message_handler/struct.py
pybotterfly/runners/__init__.py
pybotterfly/runners/tg_client.py
pybotterfly/runners/vk_client.py
pybotterfly/server/__init__.py
pybotterfly/server/server.py
pybotterfly/server/server_func.py
pybotterfly/server/struct.py
pybotterfly-0.1.6.dist-info/LICENSE
pybotterfly-0.1.6.dist-info/METADATA
pybotterfly-0.1.6.dist-info/WHEEL
pybotterfly-0.1.6.dist-info/RECORD
