Metadata-Version: 2.1
Name: pybotterfly
Version: 0.1.6
Summary: framework for creating multi-messenger bots
License: MIT
Author: Ninzalo
Author-email: k-artemiy@mail.ru
Requires-Python: >=3.11,<4.0
Classifier: License :: OSI Approved :: MIT License
Classifier: Programming Language :: Python :: 3
Classifier: Programming Language :: Python :: 3.11
Requires-Dist: aiogram (>=2.25.1,<3.0.0)
Requires-Dist: black (>=23.7.0,<24.0.0)
Requires-Dist: emoji (>=2.7.0,<3.0.0)
Requires-Dist: vkbottle (>=4.3.12,<5.0.0)
